warhammer_stats/__init__.py
warhammer_stats/attack/__init__.py
warhammer_stats/attack/attack.py
warhammer_stats/attack/multi_attack.py
warhammer_stats/attack/results.py
warhammer_stats/attack/phases/__init__.py
warhammer_stats/attack/phases/attacks_phase.py
warhammer_stats/attack/phases/damage_phase.py
warhammer_stats/attack/phases/hit_phase.py
warhammer_stats/attack/phases/kill_phase.py
warhammer_stats/attack/phases/phase.py
warhammer_stats/attack/phases/save_phase.py
warhammer_stats/attack/phases/wound_phase.py
warhammer_stats/attack/rolls/__init__.py
warhammer_stats/attack/rolls/attack_rolls.py
warhammer_stats/attack/rolls/damage_roll.py
warhammer_stats/attack/rolls/hit_rolls.py
warhammer_stats/attack/rolls/roll.py
warhammer_stats/attack/rolls/save_rolls.py
warhammer_stats/attack/rolls/wound_rolls.py
warhammer_stats/modifiers/__init__.py
warhammer_stats/modifiers/additive_modifiers.py
warhammer_stats/modifiers/generator_modifiers.py
warhammer_stats/modifiers/reroll_modifiers.py
warhammer_stats/modifiers/splitter_modifiers.py
warhammer_stats/modifiers/value_setter_modifiers.py
warhammer_stats/utils/__init__.py
warhammer_stats/utils/modifier_collection.py
warhammer_stats/utils/pmf.py
warhammer_stats/utils/target.py
warhammer_stats/utils/weapon.py
warhammer_stats-0.1.1.dist-info/LICENSE
warhammer_stats-0.1.1.dist-info/METADATA
warhammer_stats-0.1.1.dist-info/WHEEL
warhammer_stats-0.1.1.dist-info/top_level.txt
warhammer_stats-0.1.1.dist-info/RECORD
