Metadata-Version: 2.1
Name: warhammer-stats
Version: 0.1.1
Summary: Warhammer 40k stats tools
Home-page: https://github.com/akabbeke/warhammer_stats
Author: Adam Kabbeke
Author-email: akabbeke@gmail.com
Classifier: Programming Language :: Python :: 3
Classifier: License :: OSI Approved :: MIT License
Classifier: Operating System :: OS Independent
Requires-Python: >=3.6
License-File: LICENSE
Requires-Dist: numpy
Requires-Dist: mypy
